llmaix/__init__.py
llmaix/__version__.py
llmaix/cli.py
llmaix/extract.py
llmaix/utils.py
llmaix/preprocess/__init__.py
llmaix/preprocess/backends.py
llmaix/preprocess/document.py
llmaix/preprocess/engine.py
llmaix/preprocess/image_support.py
llmaix/preprocess/mime_detect.py
llmaix/preprocess/ocr_engines.py
llmaix/preprocess/utils.py
llmaix-0.0.26.dist-info/METADATA
llmaix-0.0.26.dist-info/WHEEL
llmaix-0.0.26.dist-info/entry_points.txt
llmaix-0.0.26.dist-info/licenses/LICENSE
llmaix-0.0.26.dist-info/RECORD
