Metadata-Version: 2.4
Name: llmaix
Version: 0.0.26
Summary: Add your description here
Project-URL: Homepage, http://github.com/KatherLab/llmaixlib
Project-URL: Documentation, http://github.com/KatherLab/llmaixlib
Project-URL: Issues, http://github.com/KatherLab/llmaixlib/issues
Author-email: Fabian Wolf <fabian.wolf2@tu-dresden.de>
License-Expression: MIT
License-File: LICENSE
Classifier: Operating System :: OS Independent
Classifier: Programming Language :: Python :: 3
Requires-Python: >=3.12
Requires-Dist: click~=8.2.1
Requires-Dist: filetype>=1.2.0
Requires-Dist: hatchling~=1.27.0
Requires-Dist: markitdown[docx,pdf,xls,xlsx]~=0.1.2
Requires-Dist: ocrmypdf~=16.10.4
Requires-Dist: openai>=1.102.0
Requires-Dist: pymupdf4llm==0.0.27
Requires-Dist: pymupdf~=1.26.4
Requires-Dist: pytest>=8.4.1
Provides-Extra: all
Requires-Dist: docling~=2.47.0; extra == 'all'
Requires-Dist: isort~=6.0.1; extra == 'all'
Requires-Dist: marker-pdf[full]~=1.8.5; extra == 'all'
Requires-Dist: onnxruntime; extra == 'all'
Requires-Dist: paddleocr>=3.2.0; extra == 'all'
Requires-Dist: paddlepaddle==3.1.1; extra == 'all'
Requires-Dist: paddlex[ocr]; extra == 'all'
Requires-Dist: pytest-cov~=6.2.1; extra == 'all'
Requires-Dist: pytest~=8.4.1; extra == 'all'
Requires-Dist: rapidocr-onnxruntime; extra == 'all'
Requires-Dist: rapidocr~=3.3.1; extra == 'all'
Requires-Dist: ruff~=0.12.10; extra == 'all'
Requires-Dist: ty~=0.0.1a19; extra == 'all'
Provides-Extra: dev
Requires-Dist: isort~=6.0.1; extra == 'dev'
Requires-Dist: pytest-cov~=6.2.1; extra == 'dev'
Requires-Dist: pytest~=8.4.1; extra == 'dev'
Requires-Dist: ruff~=0.12.10; extra == 'dev'
Requires-Dist: ty~=0.0.1a19; extra == 'dev'
Provides-Extra: docling
Requires-Dist: docling~=2.47.0; extra == 'docling'
Requires-Dist: onnxruntime; extra == 'docling'
Requires-Dist: rapidocr-onnxruntime; extra == 'docling'
Requires-Dist: rapidocr~=3.3.1; extra == 'docling'
Provides-Extra: marker
Requires-Dist: marker-pdf[full]~=1.8.5; extra == 'marker'
Provides-Extra: paddleocr
Requires-Dist: paddleocr>=3.2.0; extra == 'paddleocr'
Requires-Dist: paddlepaddle==3.1.1; extra == 'paddleocr'
Requires-Dist: paddlex[ocr]; extra == 'paddleocr'
